tests/__init__.py
sisu_email-0.0.6.dist-info/LICENSE
sisu_email-0.0.6.dist-info/METADATA
sisu_email-0.0.6.dist-info/WHEEL
sisu_email-0.0.6.dist-info/top_level.txt
sisu_email-0.0.6.dist-info/RECORD
